akari_proto/__init__.py
akari_proto/joints_controller_pb2.py
akari_proto/joints_controller_pb2_grpc.py
akari_proto/m5stack_pb2.py
akari_proto/m5stack_pb2_grpc.py
akari_proto/py.typed
akari_proto/grpc/__init__.py
akari_proto/grpc/error.py
akari_proto-0.4.3.dist-info/METADATA
akari_proto-0.4.3.dist-info/WHEEL
akari_proto-0.4.3.dist-info/top_level.txt
akari_proto-0.4.3.dist-info/RECORD
