Metadata-Version: 2.1
Name: akari-proto
Version: 0.4.3
Summary: Python package of akari protobuf definitions and utility functions
Home-page: https://github.com/AkariGroup/akari_software
Author: akari
Author-email: akari.tmc@gmail.com
License: Apache License 2.0
Platform: UNKNOWN
Classifier: Programming Language :: Python :: 3.6
Classifier: Programming Language :: Python :: 3.7
Classifier: Programming Language :: Python :: 3.8
Classifier: Programming Language :: Python :: 3.9
Classifier: Programming Language :: Python :: 3.10
Classifier: Programming Language :: Python :: 3.11
Classifier: Programming Language :: Python
Classifier: License :: OSI Approved :: Apache Software License
Classifier: Operating System :: POSIX
Classifier: Operating System :: Unix
Requires-Dist: grpcio==1.68.1
Requires-Dist: protobuf==5.29.2
